opem/Functions.py
opem/Params.py
opem/Profile.py
opem/Script.py
opem/__init__.py
opem/__main__.py
opem/Dynamic/Chakraborty.py
opem/Dynamic/Padulles1.py
opem/Dynamic/Padulles2.py
opem/Dynamic/Padulles_Amphlett.py
opem/Dynamic/Padulles_Hauer.py
opem/Dynamic/__init__.py
opem/Static/Amphlett.py
opem/Static/Chamberline_Kim.py
opem/Static/Larminie_Dicks.py
opem/Static/__init__.py
opem-1.4.dist-info/AUTHORS.md
opem-1.4.dist-info/LICENSE
opem-1.4.dist-info/METADATA
opem-1.4.dist-info/WHEEL
opem-1.4.dist-info/entry_points.txt
opem-1.4.dist-info/top_level.txt
opem-1.4.dist-info/RECORD
