Metadata-Version: 2.1
Name: opem
Version: 1.4
Summary: Open Source PEM Cell Simulation Tool
Home-page: https://github.com/ecsim/opem
Download-URL: https://github.com/ecsim/opem/tarball/v1.4
Author: ECSIM Development Team
Author-email: opem@ecsim.site
License: MIT
Project-URL: Webpage, http://opem.ecsim.site
Project-URL: Source, https://github.com/ecsim/opem
Keywords: OPEM PEM FC CELL Fuel-Cell Chemistry
Platform: any
Classifier: Development Status :: 5 - Production/Stable
Classifier: Intended Audience :: End Users/Desktop
Classifier: Intended Audience :: Developers
Classifier: License :: OSI Approved :: MIT License
Classifier: Operating System :: OS Independent
Classifier: Programming Language :: Python :: 3.5
Classifier: Programming Language :: Python :: 3.6
Classifier: Programming Language :: Python :: 3.7
Classifier: Programming Language :: Python :: 3.8
Classifier: Programming Language :: Python :: 3.9
Classifier: Programming Language :: Python :: 3.10
Classifier: Programming Language :: Python :: 3.11
Classifier: Programming Language :: Python :: 3.12
Classifier: Topic :: Scientific/Engineering :: Chemistry
Classifier: Topic :: Scientific/Engineering :: Physics
Requires-Python: >=3.5
License-File: LICENSE
License-File: AUTHORS.md
Requires-Dist: art >0.7
Requires-Dist: requests >=2.20.0
